SDOstreamclust
