Metadata-Version: 2.1
Name: pysdoclust-stream
Version: 0.1
Summary: SDOstreamclust is an algorithm for clustering data streams
Home-page: UNKNOWN
Author: Simon Konzett
Author-email: konzett.simon@gmail.com
License: LGPL-3.0
Platform: UNKNOWN
Requires-Python: >=3.5
